LAB3/lab3_24_character_lcd/src/lab3_character_lcd.v
`timescale 1ns/1ps
module lab3_character_lcd #(
    parameter integer TICK_CYCLES = 500,
    parameter integer POWER_TICKS = 2_000,
    parameter integer NORMAL_WAIT_TICKS = 4,
    parameter integer CLEAR_WAIT_TICKS = 200
)(
    input  wire clk_50mhz,
    input  wire rst_p,
    output reg  lcd_e,
    output reg  lcd_rs,
    output wire lcd_rw,
    output reg [7:0] lcd_data
);

    localparam integer TICK_WIDTH = (TICK_CYCLES < 2) ? 1 : $clog2(TICK_CYCLES);
    reg [TICK_WIDTH-1:0] tick_count;
    reg tick;
    reg [1:0] phase;

    reg [5:0] index;
    integer wait_count;
    integer power_count;
    reg byte_rs;
    reg [7:0] byte_data;
    assign lcd_rw = 1'b0;

    always @(posedge clk_50mhz or posedge rst_p) begin
        if (rst_p) begin
            tick_count <= 0;
            tick <= 0;
        end else if (tick_count == TICK_CYCLES - 1) begin
            tick_count <= 0;
            tick <= 1;
        end else begin
            tick_count <= tick_count + 1'b1;
            tick <= 0;
        end
    end

    always @* begin
        byte_rs = 1'b0;
        byte_data = 8'h00;
        case (index)
            0, 1, 2: byte_data = 8'h38;
            3: byte_data = 8'h0c;
            4: byte_data = 8'h06;
            5: byte_data = 8'h01;
            6: byte_data = 8'h80;
            7: begin byte_rs=1; byte_data="F"; end
            8: begin byte_rs=1; byte_data="P"; end
            9: begin byte_rs=1; byte_data="G"; end
            10: begin byte_rs=1; byte_data="A"; end
            11: begin byte_rs=1; byte_data=" "; end
            12: begin byte_rs=1; byte_data="L"; end
            13: begin byte_rs=1; byte_data="A"; end
            14: begin byte_rs=1; byte_data="B"; end
            15: begin byte_rs=1; byte_data="3"; end
            16,17,18,19,20,21,22: begin byte_rs=1; byte_data=" "; end
            23: byte_data = 8'hc0;
            24: begin byte_rs=1; byte_data="L"; end
            25: begin byte_rs=1; byte_data="C"; end
            26: begin byte_rs=1; byte_data="D"; end
            27: begin byte_rs=1; byte_data=" "; end
            28: begin byte_rs=1; byte_data="C"; end
            29: begin byte_rs=1; byte_data="O"; end
            30: begin byte_rs=1; byte_data="N"; end
            31: begin byte_rs=1; byte_data="T"; end
            32: begin byte_rs=1; byte_data="R"; end
            33: begin byte_rs=1; byte_data="O"; end
            34: begin byte_rs=1; byte_data="L"; end
            35: begin byte_rs=1; byte_data="L"; end
            36: begin byte_rs=1; byte_data="E"; end
            37: begin byte_rs=1; byte_data="R"; end
            38,39: begin byte_rs=1; byte_data=" "; end
            default: byte_data = 8'h00;
        endcase
    end

    always @(posedge clk_50mhz or posedge rst_p) begin
        if (rst_p) begin
            lcd_e <= 0; lcd_rs <= 0; lcd_data <= 0;
            phase <= 0; index <= 0; wait_count <= 0; power_count <= 0;
        end else if (tick) begin
            if (power_count < POWER_TICKS) begin
                power_count <= power_count + 1;
                lcd_e <= 0;
            end else begin
                case (phase)
                    0: begin
                        lcd_e <= 0; lcd_rs <= byte_rs; lcd_data <= byte_data;
                        phase <= 1;
                    end
                    1: begin lcd_e <= 1; phase <= 2; end
                    2: begin
                        lcd_e <= 0;
                        wait_count <= (index == 5) ? CLEAR_WAIT_TICKS : NORMAL_WAIT_TICKS;
                        phase <= 3;
                    end
                    default: begin
                        if (wait_count > 0)
                            wait_count <= wait_count - 1;
                        else begin
                            index <= (index == 39) ? 6 : index + 1'b1;
                            phase <= 0;
                        end
                    end
                endcase
            end
        end
    end
endmodule

LAB3/lab3_24_character_lcd/sim/tb_character_lcd.sv
`timescale 1ns/1ps
module tb_character_lcd;
    reg clk_50mhz=0,rst_p=1;
    wire lcd_e,lcd_rs,lcd_rw;
    wire [7:0] lcd_data;
    reg [7:0] expected_data[0:39];
    reg expected_rs[0:39];
    integer count=0,i;
    always #10 clk_50mhz=~clk_50mhz;
    lab3_character_lcd #(.TICK_CYCLES(2),.POWER_TICKS(3),.NORMAL_WAIT_TICKS(1),.CLEAR_WAIT_TICKS(2)
        ) dut
        (.clk_50mhz(clk_50mhz),.rst_p(rst_p),.lcd_e(lcd_e),.lcd_rs(lcd_rs),.lcd_rw(lcd_rw),.lcd_data(
        lcd_data));

    initial begin
        expected_data[0]=8'h38;expected_data[1]=8'h38;expected_data[2]=8'h38;
        expected_data[3]=8'h0c;expected_data[4]=8'h06;expected_data[5]=8'h01;expected_data[6]=8'h80;
        expected_data[7]="F";expected_data[8]="P";expected_data[9]="G";expected_data[10]="A";
        expected_data[11]=" ";expected_data[12]="L";expected_data[13]="A";expected_data[14]="B";
        expected_data[15]="3";
        for(i=16;i<=22;i=i+1)expected_data[i]=" ";

        expected_data[23]=8'hc0;
        expected_data[24]="L";expected_data[25]="C";expected_data[26]="D";expected_data[27]=" ";
        expected_data[28]="C";expected_data[29]="O";expected_data[30]="N";expected_data[31]="T";
        expected_data[32]="R";expected_data[33]="O";expected_data[34]="L";expected_data[35]="L";
        expected_data[36]="E";expected_data[37]="R";expected_data[38]=" ";expected_data[39]=" ";
        for(i=0;i<40;i=i+1)expected_rs[i]=(i>=7 && i!=23);
        expected_rs[38]=1;expected_rs[39]=1;
    end

    always @(negedge lcd_e) if(!rst_p && count<40)begin
        if(lcd_rw!==0||lcd_rs!==expected_rs[count]||lcd_data!==expected_data[count])
            $fatal(1,"index=%0d rs=%b data=%h",count,lcd_rs,lcd_data);
        count=count+1;
        if(count==40)begin $display("LAB3_LCD_PASS bytes=%0d",count);$finish;end
    end

    initial begin
        $dumpfile("wave.vcd");$dumpvars(0,tb_character_lcd);
        repeat(3)@(posedge clk_50mhz);rst_p=0;
    end

    initial begin #50000;$fatal(1,"timeout count=%0d",count);end
endmodule

LAB3/lab3_24_character_lcd/build/sim/run-ec1673b523f74472a3ddebc23287bc3e/wave.vcd
$date
	Mon Sep 28 05:15:00 2026
$end
$version
	Icarus Verilog
$end
$timescale
	1ps
$end
$scope module tb_character_lcd $end
$var wire 1 ! lcd_rw $end
$var wire 1 " lcd_rs $end
$var wire 1 # lcd_e $end
$var wire 8 $ lcd_data [7:0] $end
$var reg 1 % clk_50mhz $end
$var reg 1 & rst_p $end
$var integer 32 ' count [31:0] $end
$var integer 32 ( i [31:0] $end
$scope module dut $end
$var wire 1 % clk_50mhz $end
$var wire 1 ! lcd_rw $end
$var wire 1 & rst_p $end
$var parameter 32 ) CLEAR_WAIT_TICKS $end
$var parameter 32 * NORMAL_WAIT_TICKS $end
$var parameter 32 + POWER_TICKS $end
$var parameter 32 , TICK_CYCLES $end
$var parameter 32 - TICK_WIDTH $end
$var reg 8 . byte_data [7:0] $end
$var reg 1 / byte_rs $end
$var reg 6 0 index [5:0] $end
$var reg 8 1 lcd_data [7:0] $end
$var reg 1 # lcd_e $end
$var reg 1 " lcd_rs $end
$var reg 2 2 phase [1:0] $end
$var reg 1 3 tick $end
$var reg 1 4 tick_count $end
$var integer 32 5 power_count [31:0] $end
$var integer 32 6 wait_count [31:0] $end
$upscope $end
$upscope $end
$enddefinitions $end
$comment Show the parameter values. $end
$dumpall
b1 -
b10 ,
b11 +
b1 *
b10 )
$end
#0
$dumpvars
bx 6
bx 5
x4
x3
bx 2
bx 1
bx 0
x/
bx .
b101000 (
b0 '
1&
0%
bx $
x#
x"
0!
$end
#10000
b111000 .
0/
03
04
b0 5
b0 6
b0 0
b0 2
b0 $
b0 1
0"
0#
1%
#20000
0%
#30000
1%
#40000
0%
#50000
14
0&
1%
#60000
0%
#70000
13
04
1%
#80000
0%
#90000
03
14
b1 5
1%
#100000
0%
#110000
13
04
1%
#120000
0%
#130000
03
14
b10 5
1%
#140000
0%
#150000
13
04
1%
#160000
0%
#170000
03
14
b11 5
1%
#180000
0%
#190000
13
04
1%
#200000
0%
#210000
03
14
b1 2
b111000 $
b111000 1
1%
#220000
0%
#230000
13
04
1%
#240000
0%
#250000
03
14
b10 2
1#
1%
#260000
0%
#270000
13
04
1%
#280000
0%
#290000
b1 '
03
14
b11 2
b1 6
0#
1%
#300000
0%
#310000
13
04
1%
#320000
0%
#330000
03
14
b0 6
1%
#340000
0%
#350000
13
04
1%
#360000
0%
#370000
b111000 .
03
14
b0 2
b1 0
1%
#380000
0%
#390000
13
04
1%
#400000
0%
#410000
03
14
b1 2
1%
#420000
0%
#430000
13
04
1%
#440000
0%
#450000
03
14
b10 2
1#
1%
#460000
0%
#470000
13
04
1%
#480000
0%
#490000
b10 '
03
14
b11 2
b1 6
0#
1%
#500000
0%
#510000
13
04
1%
#520000
0%
#530000
03
14
b0 6
1%
#540000
0%
#550000
13
04
1%
#560000
0%
#570000
b111000 .
03
14
b0 2
b10 0
1%
#580000
0%
#590000
13
04
1%
#600000
0%
#610000
03
14
b1 2
1%
#620000
0%
#630000
13
04
1%
#640000
0%
#650000
03
14
b10 2
1#
1%
#660000
0%
#670000
13
04
1%
#680000
0%
#690000
b11 '
03
14
b11 2
b1 6
0#
1%
#700000
0%
#710000
13
04
1%
#720000
0%
#730000
03
14
b0 6
1%
#740000
0%
#750000
13
04
1%
#760000
0%
#770000
b1100 .
03
14
b0 2
b11 0
1%
#780000
0%
#790000
13
04
1%
#800000
0%
#810000
03
14
b1 2
b1100 $
b1100 1
1%
#820000
0%
#830000
13
04
1%
#840000
0%
#850000
03
14
b10 2
1#
1%
#860000
0%
#870000
13
04
1%
#880000
0%
#890000
b100 '
03
14
b11 2
b1 6
0#
1%
#900000
0%
#910000
13
04
1%
#920000
0%
#930000
03
14
b0 6
1%
#940000
0%
#950000
13
04
1%
#960000
0%
#970000
b110 .
03
14
b0 2
b100 0
1%
#980000
0%
#990000
13
04
1%
#1000000
0%
#1010000
03
14
b1 2
b110 $
b110 1
1%
#1020000
0%
#1030000
13
04
1%
#1040000
0%
#1050000
03
14
b10 2
1#
1%
#1060000
0%
#1070000
13
04
1%
#1080000
0%
#1090000
b101 '
03
14
b11 2
b1 6
0#
1%
#1100000
0%
#1110000
13
04
1%
#1120000
0%
#1130000
03
14
b0 6
1%
#1140000
0%
#1150000
13
04
1%
#1160000
0%
#1170000
b1 .
03
14
b0 2
b101 0
1%
#1180000
0%
#1190000
13
04
1%
#1200000
0%
#1210000
03
14
b1 2
b1 $
b1 1
1%
#1220000
0%
#1230000
13
04
1%
#1240000
0%
#1250000
03
14
b10 2
1#
1%
#1260000
0%
#1270000
13
04
1%
#1280000
0%
#1290000
b110 '
03
14
b11 2
b10 6
0#
1%
#1300000
0%
#1310000
13
04
1%
#1320000
0%
#1330000
03
14
b1 6
1%
#1340000
0%
#1350000
13
04
1%
#1360000
0%
#1370000
03
14
b0 6
1%
#1380000
0%
#1390000
13
04
1%
#1400000
0%
#1410000
b10000000 .
03
14
b0 2
b110 0
1%
#1420000
0%
#1430000
13
04
1%
#1440000
0%
#1450000
03
14
b1 2
b10000000 $
b10000000 1
1%
#1460000
0%
#1470000
13
04
1%
#1480000
0%
#1490000
03
14
b10 2
1#
1%
#1500000
0%
#1510000
13
04
1%
#1520000
0%
#1530000
b111 '
03
14
b11 2
b1 6
0#
1%
#1540000
0%
#1550000
13
04
1%
#1560000
0%
#1570000
03
14
b0 6
1%
#1580000
0%
#1590000
13
04
1%
#1600000
0%
#1610000
1/
b1000110 .
03
14
b0 2
b111 0
1%
#1620000
0%
#1630000
13
04
1%
#1640000
0%
#1650000
03
14
b1 2
b1000110 $
b1000110 1
1"
1%
#1660000
0%
#1670000
13
04
1%
#1680000
0%
#1690000
03
14
b10 2
1#
1%
#1700000
0%
#1710000
13
04
1%
#1720000
0%
#1730000
b1000 '
03
14
b11 2
b1 6
0#
1%
#1740000
0%
#1750000
13
04
1%
#1760000
0%
#1770000
03
14
b0 6
1%
#1780000
0%
#1790000
13
04
1%
#1800000
0%
#1810000
b1010000 .
1/
03
14
b0 2
b1000 0
1%
#1820000
0%
#1830000
13
04
1%
#1840000
0%
#1850000
03
14
b1 2
b1010000 $
b1010000 1
1%
#1860000
0%
#1870000
13
04
1%
#1880000
0%
#1890000
03
14
b10 2
1#
1%
#1900000
0%
#1910000
13
04
1%
#1920000
0%
#1930000
b1001 '
03
14
b11 2
b1 6
0#
1%
#1940000
0%
#1950000
13
04
1%
#1960000
0%
#1970000
03
14
b0 6
1%
#1980000
0%
#1990000
13
04
1%
#2000000
0%
#2010000
b1000111 .
1/
03
14
b0 2
b1001 0
1%
#2020000
0%
#2030000
13
04
1%
#2040000
0%
#2050000
03
14
b1 2
b1000111 $
b1000111 1
1%
#2060000
0%
#2070000
13
04
1%
#2080000
0%
#2090000
03
14
b10 2
1#
1%
#2100000
0%
#2110000
13
04
1%
#2120000
0%
#2130000
b1010 '
03
14
b11 2
b1 6
0#
1%
#2140000
0%
#2150000
13
04
1%
#2160000
0%
#2170000
03
14
b0 6
1%
#2180000
0%
#2190000
13
04
1%
#2200000
0%
#2210000
b1000001 .
1/
03
14
b0 2
b1010 0
1%
#2220000
0%
#2230000
13
04
1%
#2240000
0%
#2250000
03
14
b1 2
b1000001 $
b1000001 1
1%
#2260000
0%
#2270000
13
04
1%
#2280000
0%
#2290000
03
14
b10 2
1#
1%
#2300000
0%
#2310000
13
04
1%
#2320000
0%
#2330000
b1011 '
03
14
b11 2
b1 6
0#
1%
#2340000
0%
#2350000
13
04
1%
#2360000
0%
#2370000
03
14
b0 6
1%
#2380000
0%
#2390000
13
04
1%
#2400000
0%
#2410000
b100000 .
1/
03
14
b0 2
b1011 0
1%
#2420000
0%
#2430000
13
04
1%
#2440000
0%
#2450000
03
14
b1 2
b100000 $
b100000 1
1%
#2460000
0%
#2470000
13
04
1%
#2480000
0%
#2490000
03
14
b10 2
1#
1%
#2500000
0%
#2510000
13
04
1%
#2520000
0%
#2530000
b1100 '
03
14
b11 2
b1 6
0#
1%
#2540000
0%
#2550000
13
04
1%
#2560000
0%
#2570000
03
14
b0 6
1%
#2580000
0%
#2590000
13
04
1%
#2600000
0%
#2610000
b1001100 .
1/
03
14
b0 2
b1100 0
1%
#2620000
0%
#2630000
13
04
1%
#2640000
0%
#2650000
03
14
b1 2
b1001100 $
b1001100 1
1%
#2660000
0%
#2670000
13
04
1%
#2680000
0%
#2690000
03
14
b10 2
1#
1%
#2700000
0%
#2710000
13
04
1%
#2720000
0%
#2730000
b1101 '
03
14
b11 2
b1 6
0#
1%
#2740000
0%
#2750000
13
04
1%
#2760000
0%
#2770000
03
14
b0 6
1%
#2780000
0%
#2790000
13
04
1%
#2800000
0%
#2810000
b1000001 .
1/
03
14
b0 2
b1101 0
1%
#2820000
0%
#2830000
13
04
1%
#2840000
0%
#2850000
03
14
b1 2
b1000001 $
b1000001 1
1%
#2860000
0%
#2870000
13
04
1%
#2880000
0%
#2890000
03
14
b10 2
1#
1%
#2900000
0%
#2910000
13
04
1%
#2920000
0%
#2930000
b1110 '
03
14
b11 2
b1 6
0#
1%
#2940000
0%
#2950000
13
04
1%
#2960000
0%
#2970000
03
14
b0 6
1%
#2980000
0%
#2990000
13
04
1%
#3000000
0%
#3010000
b1000010 .
1/
03
14
b0 2
b1110 0
1%
#3020000
0%
#3030000
13
04
1%
#3040000
0%
#3050000
03
14
b1 2
b1000010 $
b1000010 1
1%
#3060000
0%
#3070000
13
04
1%
#3080000
0%
#3090000
03
14
b10 2
1#
1%
#3100000
0%
#3110000
13
04
1%
#3120000
0%
#3130000
b1111 '
03
14
b11 2
b1 6
0#
1%
#3140000
0%
#3150000
13
04
1%
#3160000
0%
#3170000
03
14
b0 6
1%
#3180000
0%
#3190000
13
04
1%
#3200000
0%
#3210000
b110011 .
1/
03
14
b0 2
b1111 0
1%
#3220000
0%
#3230000
13
04
1%
#3240000
0%
#3250000
03
14
b1 2
b110011 $
b110011 1
1%
#3260000
0%
#3270000
13
04
1%
#3280000
0%
#3290000
03
14
b10 2
1#
1%
#3300000
0%
#3310000
13
04
1%
#3320000
0%
#3330000
b10000 '
03
14
b11 2
b1 6
0#
1%
#3340000
0%
#3350000
13
04
1%
#3360000
0%
#3370000
03
14
b0 6
1%
#3380000
0%
#3390000
13
04
1%
#3400000
0%
#3410000
b100000 .
1/
03
14
b0 2
b10000 0
1%
#3420000
0%
#3430000
13
04
1%
#3440000
0%
#3450000
03
14
b1 2
b100000 $
b100000 1
1%
#3460000
0%
#3470000
13
04
1%
#3480000
0%
#3490000
03
14
b10 2
1#
1%
#3500000
0%
#3510000
13
04
1%
#3520000
0%
#3530000
b10001 '
03
14
b11 2
b1 6
0#
1%
#3540000
0%
#3550000
13
04
1%
#3560000
0%
#3570000
03
14
b0 6
1%
#3580000
0%
#3590000
13
04
1%
#3600000
0%
#3610000
b100000 .
1/
03
14
b0 2
b10001 0
1%
#3620000
0%
#3630000
13
04
1%
#3640000
0%
#3650000
03
14
b1 2
1%
#3660000
0%
#3670000
13
04
1%
#3680000
0%
#3690000
03
14
b10 2
1#
1%
#3700000
0%
#3710000
13
04
1%
#3720000
0%
#3730000
b10010 '
03
14
b11 2
b1 6
0#
1%
#3740000
0%
#3750000
13
04
1%
#3760000
0%
#3770000
03
14
b0 6
1%
#3780000
0%
#3790000
13
04
1%
#3800000
0%
#3810000
b100000 .
1/
03
14
b0 2
b10010 0
1%
#3820000
0%
#3830000
13
04
1%
#3840000
0%
#3850000
03
14
b1 2
1%
#3860000
0%
#3870000
13
04
1%
#3880000
0%
#3890000
03
14
b10 2
1#
1%
#3900000
0%
#3910000
13
04
1%
#3920000
0%
#3930000
b10011 '
03
14
b11 2
b1 6
0#
1%
#3940000
0%
#3950000
13
04
1%
#3960000
0%
#3970000
03
14
b0 6
1%
#3980000
0%
#3990000
13
04
1%
#4000000
0%
#4010000
b100000 .
1/
03
14
b0 2
b10011 0
1%
#4020000
0%
#4030000
13
04
1%
#4040000
0%
#4050000
03
14
b1 2
1%
#4060000
0%
#4070000
13
04
1%
#4080000
0%
#4090000
03
14
b10 2
1#
1%
#4100000
0%
#4110000
13
04
1%
#4120000
0%
#4130000
b10100 '
03
14
b11 2
b1 6
0#
1%
#4140000
0%
#4150000
13
04
1%
#4160000
0%
#4170000
03
14
b0 6
1%
#4180000
0%
#4190000
13
04
1%
#4200000
0%
#4210000
b100000 .
1/
03
14
b0 2
b10100 0
1%
#4220000
0%
#4230000
13
04
1%
#4240000
0%
#4250000
03
14
b1 2
1%
#4260000
0%
#4270000
13
04
1%
#4280000
0%
#4290000
03
14
b10 2
1#
1%
#4300000
0%
#4310000
13
04
1%
#4320000
0%
#4330000
b10101 '
03
14
b11 2
b1 6
0#
1%
#4340000
0%
#4350000
13
04
1%
#4360000
0%
#4370000
03
14
b0 6
1%
#4380000
0%
#4390000
13
04
1%
#4400000
0%
#4410000
b100000 .
1/
03
14
b0 2
b10101 0
1%
#4420000
0%
#4430000
13
04
1%
#4440000
0%
#4450000
03
14
b1 2
1%
#4460000
0%
#4470000
13
04
1%
#4480000
0%
#4490000
03
14
b10 2
1#
1%
#4500000
0%
#4510000
13
04
1%
#4520000
0%
#4530000
b10110 '
03
14
b11 2
b1 6
0#
1%
#4540000
0%
#4550000
13
04
1%
#4560000
0%
#4570000
03
14
b0 6
1%
#4580000
0%
#4590000
13
04
1%
#4600000
0%
#4610000
b100000 .
1/
03
14
b0 2
b10110 0
1%
#4620000
0%
#4630000
13
04
1%
#4640000
0%
#4650000
03
14
b1 2
1%
#4660000
0%
#4670000
13
04
1%
#4680000
0%
#4690000
03
14
b10 2
1#
1%
#4700000
0%
#4710000
13
04
1%
#4720000
0%
#4730000
b10111 '
03
14
b11 2
b1 6
0#
1%
#4740000
0%
#4750000
13
04
1%
#4760000
0%
#4770000
03
14
b0 6
1%
#4780000
0%
#4790000
13
04
1%
#4800000
0%
#4810000
b11000000 .
0/
03
14
b0 2
b10111 0
1%
#4820000
0%
#4830000
13
04
1%
#4840000
0%
#4850000
03
14
b1 2
b11000000 $
b11000000 1
0"
1%
#4860000
0%
#4870000
13
04
1%
#4880000
0%
#4890000
03
14
b10 2
1#
1%
#4900000
0%
#4910000
13
04
1%
#4920000
0%
#4930000
b11000 '
03
14
b11 2
b1 6
0#
1%
#4940000
0%
#4950000
13
04
1%
#4960000
0%
#4970000
03
14
b0 6
1%
#4980000
0%
#4990000
13
04
1%
#5000000
0%
#5010000
1/
b1001100 .
03
14
b0 2
b11000 0
1%
#5020000
0%
#5030000
13
04
1%
#5040000
0%
#5050000
03
14
b1 2
b1001100 $
b1001100 1
1"
1%
#5060000
0%
#5070000
13
04
1%
#5080000
0%
#5090000
03
14
b10 2
1#
1%
#5100000
0%
#5110000
13
04
1%
#5120000
0%
#5130000
b11001 '
03
14
b11 2
b1 6
0#
1%
#5140000
0%
#5150000
13
04
1%
#5160000
0%
#5170000
03
14
b0 6
1%
#5180000
0%
#5190000
13
04
1%
#5200000
0%
#5210000
b1000011 .
1/
03
14
b0 2
b11001 0
1%
#5220000
0%
#5230000
13
04
1%
#5240000
0%
#5250000
03
14
b1 2
b1000011 $
b1000011 1
1%
#5260000
0%
#5270000
13
04
1%
#5280000
0%
#5290000
03
14
b10 2
1#
1%
#5300000
0%
#5310000
13
04
1%
#5320000
0%
#5330000
b11010 '
03
14
b11 2
b1 6
0#
1%
#5340000
0%
#5350000
13
04
1%
#5360000
0%
#5370000
03
14
b0 6
1%
#5380000
0%
#5390000
13
04
1%
#5400000
0%
#5410000
b1000100 .
1/
03
14
b0 2
b11010 0
1%
#5420000
0%
#5430000
13
04
1%
#5440000
0%
#5450000
03
14
b1 2
b1000100 $
b1000100 1
1%
#5460000
0%
#5470000
13
04
1%
#5480000
0%
#5490000
03
14
b10 2
1#
1%
#5500000
0%
#5510000
13
04
1%
#5520000
0%
#5530000
b11011 '
03
14
b11 2
b1 6
0#
1%
#5540000
0%
#5550000
13
04
1%
#5560000
0%
#5570000
03
14
b0 6
1%
#5580000
0%
#5590000
13
04
1%
#5600000
0%
#5610000
b100000 .
1/
03
14
b0 2
b11011 0
1%
#5620000
0%
#5630000
13
04
1%
#5640000
0%
#5650000
03
14
b1 2
b100000 $
b100000 1
1%
#5660000
0%
#5670000
13
04
1%
#5680000
0%
#5690000
03
14
b10 2
1#
1%
#5700000
0%
#5710000
13
04
1%
#5720000
0%
#5730000
b11100 '
03
14
b11 2
b1 6
0#
1%
#5740000
0%
#5750000
13
04
1%
#5760000
0%
#5770000
03
14
b0 6
1%
#5780000
0%
#5790000
13
04
1%
#5800000
0%
#5810000
b1000011 .
1/
03
14
b0 2
b11100 0
1%
#5820000
0%
#5830000
13
04
1%
#5840000
0%
#5850000
03
14
b1 2
b1000011 $
b1000011 1
1%
#5860000
0%
#5870000
13
04
1%
#5880000
0%
#5890000
03
14
b10 2
1#
1%
#5900000
0%
#5910000
13
04
1%
#5920000
0%
#5930000
b11101 '
03
14
b11 2
b1 6
0#
1%
#5940000
0%
#5950000
13
04
1%
#5960000
0%
#5970000
03
14
b0 6
1%
#5980000
0%
#5990000
13
04
1%
#6000000
0%
#6010000
b1001111 .
1/
03
14
b0 2
b11101 0
1%
#6020000
0%
#6030000
13
04
1%
#6040000
0%
#6050000
03
14
b1 2
b1001111 $
b1001111 1
1%
#6060000
0%
#6070000
13
04
1%
#6080000
0%
#6090000
03
14
b10 2
1#
1%
#6100000
0%
#6110000
13
04
1%
#6120000
0%
#6130000
b11110 '
03
14
b11 2
b1 6
0#
1%
#6140000
0%
#6150000
13
04
1%
#6160000
0%
#6170000
03
14
b0 6
1%
#6180000
0%
#6190000
13
04
1%
#6200000
0%
#6210000
b1001110 .
1/
03
14
b0 2
b11110 0
1%
#6220000
0%
#6230000
13
04
1%
#6240000
0%
#6250000
03
14
b1 2
b1001110 $
b1001110 1
1%
#6260000
0%
#6270000
13
04
1%
#6280000
0%
#6290000
03
14
b10 2
1#
1%
#6300000
0%
#6310000
13
04
1%
#6320000
0%
#6330000
b11111 '
03
14
b11 2
b1 6
0#
1%
#6340000
0%
#6350000
13
04
1%
#6360000
0%
#6370000
03
14
b0 6
1%
#6380000
0%
#6390000
13
04
1%
#6400000
0%
#6410000
b1010100 .
1/
03
14
b0 2
b11111 0
1%
#6420000
0%
#6430000
13
04
1%
#6440000
0%
#6450000
03
14
b1 2
b1010100 $
b1010100 1
1%
#6460000
0%
#6470000
13
04
1%
#6480000
0%
#6490000
03
14
b10 2
1#
1%
#6500000
0%
#6510000
13
04
1%
#6520000
0%
#6530000
b100000 '
03
14
b11 2
b1 6
0#
1%
#6540000
0%
#6550000
13
04
1%
#6560000
0%
#6570000
03
14
b0 6
1%
#6580000
0%
#6590000
13
04
1%
#6600000
0%
#6610000
b1010010 .
1/
03
14
b0 2
b100000 0
1%
#6620000
0%
#6630000
13
04
1%
#6640000
0%
#6650000
03
14
b1 2
b1010010 $
b1010010 1
1%
#6660000
0%
#6670000
13
04
1%
#6680000
0%
#6690000
03
14
b10 2
1#
1%
#6700000
0%
#6710000
13
04
1%
#6720000
0%
#6730000
b100001 '
03
14
b11 2
b1 6
0#
1%
#6740000
0%
#6750000
13
04
1%
#6760000
0%
#6770000
03
14
b0 6
1%
#6780000
0%
#6790000
13
04
1%
#6800000
0%
#6810000
b1001111 .
1/
03
14
b0 2
b100001 0
1%
#6820000
0%
#6830000
13
04
1%
#6840000
0%
#6850000
03
14
b1 2
b1001111 $
b1001111 1
1%
#6860000
0%
#6870000
13
04
1%
#6880000
0%
#6890000
03
14
b10 2
1#
1%
#6900000
0%
#6910000
13
04
1%
#6920000
0%
#6930000
b100010 '
03
14
b11 2
b1 6
0#
1%
#6940000
0%
#6950000
13
04
1%
#6960000
0%
#6970000
03
14
b0 6
1%
#6980000
0%
#6990000
13
04
1%
#7000000
0%
#7010000
b1001100 .
1/
03
14
b0 2
b100010 0
1%
#7020000
0%
#7030000
13
04
1%
#7040000
0%
#7050000
03
14
b1 2
b1001100 $
b1001100 1
1%
#7060000
0%
#7070000
13
04
1%
#7080000
0%
#7090000
03
14
b10 2
1#
1%
#7100000
0%
#7110000
13
04
1%
#7120000
0%
#7130000
b100011 '
03
14
b11 2
b1 6
0#
1%
#7140000
0%
#7150000
13
04
1%
#7160000
0%
#7170000
03
14
b0 6
1%
#7180000
0%
#7190000
13
04
1%
#7200000
0%
#7210000
b1001100 .
1/
03
14
b0 2
b100011 0
1%
#7220000
0%
#7230000
13
04
1%
#7240000
0%
#7250000
03
14
b1 2
1%
#7260000
0%
#7270000
13
04
1%
#7280000
0%
#7290000
03
14
b10 2
1#
1%
#7300000
0%
#7310000
13
04
1%
#7320000
0%
#7330000
b100100 '
03
14
b11 2
b1 6
0#
1%
#7340000
0%
#7350000
13
04
1%
#7360000
0%
#7370000
03
14
b0 6
1%
#7380000
0%
#7390000
13
04
1%
#7400000
0%
#7410000
b1000101 .
1/
03
14
b0 2
b100100 0
1%
#7420000
0%
#7430000
13
04
1%
#7440000
0%
#7450000
03
14
b1 2
b1000101 $
b1000101 1
1%
#7460000
0%
#7470000
13
04
1%
#7480000
0%
#7490000
03
14
b10 2
1#
1%
#7500000
0%
#7510000
13
04
1%
#7520000
0%
#7530000
b100101 '
03
14
b11 2
b1 6
0#
1%
#7540000
0%
#7550000
13
04
1%
#7560000
0%
#7570000
03
14
b0 6
1%
#7580000
0%
#7590000
13
04
1%
#7600000
0%
#7610000
b1010010 .
1/
03
14
b0 2
b100101 0
1%
#7620000
0%
#7630000
13
04
1%
#7640000
0%
#7650000
03
14
b1 2
b1010010 $
b1010010 1
1%
#7660000
0%
#7670000
13
04
1%
#7680000
0%
#7690000
03
14
b10 2
1#
1%
#7700000
0%
#7710000
13
04
1%
#7720000
0%
#7730000
b100110 '
03
14
b11 2
b1 6
0#
1%
#7740000
0%
#7750000
13
04
1%
#7760000
0%
#7770000
03
14
b0 6
1%
#7780000
0%
#7790000
13
04
1%
#7800000
0%
#7810000
b100000 .
1/
03
14
b0 2
b100110 0
1%
#7820000
0%
#7830000
13
04
1%
#7840000
0%
#7850000
03
14
b1 2
b100000 $
b100000 1
1%
#7860000
0%
#7870000
13
04
1%
#7880000
0%
#7890000
03
14
b10 2
1#
1%
#7900000
0%
#7910000
13
04
1%
#7920000
0%
#7930000
b100111 '
03
14
b11 2
b1 6
0#
1%
#7940000
0%
#7950000
13
04
1%
#7960000
0%
#7970000
03
14
b0 6
1%
#7980000
0%
#7990000
13
04
1%
#8000000
0%
#8010000
b100000 .
1/
03
14
b0 2
b100111 0
1%
#8020000
0%
#8030000
13
04
1%
#8040000
0%
#8050000
03
14
b1 2
1%
#8060000
0%
#8070000
13
04
1%
#8080000
0%
#8090000
03
14
b10 2
1#
1%
#8100000
0%
#8110000
13
04
1%
#8120000
0%
#8130000
b101000 '
03
14
b11 2
b1 6
0#
1%
