LAB2/lab2_06_moore/src/moore_cycle.v
`timescale 1ns/1ps
module moore_cycle (
    input wire clk, input wire rst, input wire enable, input wire advance,
    output reg [1:0] value
);

    always @(posedge clk) begin
        if (rst)
            value <= 2'b00;
        else if (enable && advance) begin
            case (value)
                2'b00: value <= 2'b01;
                2'b01: value <= 2'b10;
                default: value <= 2'b00;
            endcase
        end
    end

endmodule

LAB2/lab2_06_moore/sim/tb_moore_cycle.sv
`timescale 1ns/1ps

module tb_moore_cycle;

    reg clk=0, rst=1;
    integer checks=0;

    always #5 clk=~clk;

    task step;
    begin
        @(posedge clk);
        #1;
    end
    endtask

    task check(input condition, input [8*100-1:0] description);
    begin
        checks=checks+1;
        if (condition !== 1'b1) begin
            $display("LAB2_FAIL %0s time=%0t",description,$time);
            $fatal(1,"check failed");
        end
    end
    endtask

    task finish;
    begin
        $display("LAB2_PASS moore_cycle checks=%0d",checks);
        $finish;
    end
    endtask

    initial begin
        $dumpfile("wave.vcd");
        $dumpvars(0,tb_moore_cycle);
    end

    initial begin
        #100000;
        $fatal(1,"watchdog timeout");
    end

    reg enable=0, advance=0;
    wire [1:0] value;

    moore_cycle dut(
        clk,
        rst,
        enable,
        advance,
        value
    );

    integer round;

    initial begin
        step;
        check(value===0,"reset");
        rst=0;
        enable=1;

        advance=1;
        #1;
        check(value===0,"input alone cannot change output");

        for(round=0; round<4; round=round+1) begin
            step;
            check(value===1,"S0 to S1");

            advance=0;
            step;
            check(value===1,"advance zero holds");

            advance=1;
            enable=0;
            step;
            check(value===1,"disabled holds");

            enable=1;
            step;
            check(value===2,"S1 to S2");

            step;
            check(value===0,"S2 to S0");
        end

        step;
        rst=1;
        step;
        check(value===0,"reset from nonzero");

        finish;
    end

endmodule

LAB2/lab2_06_moore/build/sim/run-a07c9fa58e5a49aea81d9792f61e6c34/wave.vcd
$date
	Mon Sep 21 12:49:03 2026
$end
$version
	Icarus Verilog
$end
$timescale
	1ps
$end
$scope module tb_moore_cycle $end
$var wire 2 ! value [1:0] $end
$var reg 1 " advance $end
$var reg 1 # clk $end
$var reg 1 $ enable $end
$var reg 1 % rst $end
$var integer 32 & checks [31:0] $end
$var integer 32 ' round [31:0] $end
$scope module dut $end
$var wire 1 " advance $end
$var wire 1 # clk $end
$var wire 1 $ enable $end
$var wire 1 % rst $end
$var reg 2 ( value [1:0] $end
$upscope $end
$scope task check $end
$var reg 1 ) condition $end
$var reg 800 * description [799:0] $end
$upscope $end
$scope task finish $end
$upscope $end
$scope task step $end
$upscope $end
$upscope $end
$enddefinitions $end
$comment Show the parameter values. $end
$dumpall
$end
#0
$dumpvars
bx *
x)
bx (
bx '
b0 &
1%
0$
0#
0"
bx !
$end
#5000
b0 !
b0 (
1#
#6000
1"
1$
0%
b1 &
b111001001100101011100110110010101110100 *
1)
#7000
b0 '
b10 &
b110100101101110011100000111010101110100001000000110000101101100011011110110111001100101001000000110001101100001011011100110111001101111011101000010000001100011011010000110000101101110011001110110010100100000011011110111010101110100011100000111010101110100 *
#10000
0#
#15000
b1 !
b1 (
1#
#16000
0"
b11 &
b101001100110000001000000111010001101111001000000101001100110001 *
#20000
0#
#25000
1#
#26000
0$
1"
b100 &
b11000010110010001110110011000010110111001100011011001010010000001111010011001010111001001101111001000000110100001101111011011000110010001110011 *
#30000
0#
#35000
1#
#36000
1$
b101 &
b110010001101001011100110110000101100010011011000110010101100100001000000110100001101111011011000110010001110011 *
#40000
0#
#45000
b10 !
b10 (
1#
#46000
b110 &
b101001100110001001000000111010001101111001000000101001100110010 *
#50000
0#
#55000
b0 !
b0 (
1#
#56000
b1 '
b111 &
b101001100110010001000000111010001101111001000000101001100110000 *
#60000
0#
#65000
b1 !
b1 (
1#
#66000
0"
b1000 &
b101001100110000001000000111010001101111001000000101001100110001 *
#70000
0#
#75000
1#
#76000
0$
1"
b1001 &
b11000010110010001110110011000010110111001100011011001010010000001111010011001010111001001101111001000000110100001101111011011000110010001110011 *
#80000
0#
#85000
1#
#86000
1$
b1010 &
b110010001101001011100110110000101100010011011000110010101100100001000000110100001101111011011000110010001110011 *
#90000
0#
#95000
b10 !
b10 (
1#
#96000
b1011 &
b101001100110001001000000111010001101111001000000101001100110010 *
#100000
0#
#105000
b0 !
b0 (
1#
#106000
b10 '
b1100 &
b101001100110010001000000111010001101111001000000101001100110000 *
#110000
0#
#115000
b1 !
b1 (
1#
#116000
0"
b1101 &
b101001100110000001000000111010001101111001000000101001100110001 *
#120000
0#
#125000
1#
#126000
0$
1"
b1110 &
b11000010110010001110110011000010110111001100011011001010010000001111010011001010111001001101111001000000110100001101111011011000110010001110011 *
#130000
0#
#135000
1#
#136000
1$
b1111 &
b110010001101001011100110110000101100010011011000110010101100100001000000110100001101111011011000110010001110011 *
#140000
0#
#145000
b10 !
b10 (
1#
#146000
b10000 &
b101001100110001001000000111010001101111001000000101001100110010 *
#150000
0#
#155000
b0 !
b0 (
1#
#156000
b11 '
b10001 &
b101001100110010001000000111010001101111001000000101001100110000 *
#160000
0#
#165000
b1 !
b1 (
1#
#166000
0"
b10010 &
b101001100110000001000000111010001101111001000000101001100110001 *
#170000
0#
#175000
1#
#176000
0$
1"
b10011 &
b11000010110010001110110011000010110111001100011011001010010000001111010011001010111001001101111001000000110100001101111011011000110010001110011 *
#180000
0#
#185000
1#
#186000
1$
b10100 &
b110010001101001011100110110000101100010011011000110010101100100001000000110100001101111011011000110010001110011 *
#190000
0#
#195000
b10 !
b10 (
1#
#196000
b10101 &
b101001100110001001000000111010001101111001000000101001100110010 *
#200000
0#
#205000
b0 !
b0 (
1#
#206000
b100 '
b10110 &
b101001100110010001000000111010001101111001000000101001100110000 *
#210000
0#
#215000
b1 !
b1 (
1#
#216000
1%
#220000
0#
#225000
b0 !
b0 (
1#
#226000
b10111 &
b11100100110010101110011011001010111010000100000011001100111001001101111011011010010000001101110011011110110111001111010011001010111001001101111 *
