LAB1/lab1_02_full_adder/src/half_adder.v
module half_adder(
    input a,
    input b,
    output s,
    output c
);

assign s = a ^ b; // Sum output
assign c = a & b; // Carry output

endmodule

LAB1/lab1_02_full_adder/src/full_adder.v
module full_adder(
    input a,
    input b,
    input cin,
    output s,
    output cout
);

wire sum1;
wire carry1;
wire carry2;

half_adder HA1 (
    .a(a),
    .b(b),
    .s(sum1),
    .c(carry1)
);

half_adder HA2 (
    .a(sum1),
    .b(cin),
    .s(s),
    .c(carry2)
);

assign cout = carry1 | carry2; // Final carry output

endmodule

LAB1/lab1_02_full_adder/sim/tb_full_adder.sv
`timescale 1ns/1ps

module tb_full_adder;

    reg a,b,cin; wire s,cout; full_adder dut(a,b,cin,s,cout);
    integer n,checked=0;
    reg [1:0] expected;
    
    initial begin
        $dumpfile("wave.vcd");
        $dumpvars(0,tb_full_adder);

        for(n=0;n<8;n=n+1) begin
            {a,b,cin} = n;
            expected = int'(a)+int'(b)+int'(cin);
            #10;
            if({cout,s} !== expected)
                $fatal(1, "FAIL full_adder vector=%0d expected=%h actual=%h", n, expected, {cout,s});
            checked = checked + 1;
        end

        if(checked != 8) $fatal(1, "Incomplete test");
        $display("LAB1_PASS full_adder cases=%0d", checked);
        $finish;
    end
    initial begin
        #100000;
        $fatal(1, "Watchdog"); end

endmodule

LAB1/lab1_02_full_adder/build/sim/run-50e69e7571924c1b8ad679901dc68e74/wave.vcd
$date
	Sun Sep 13 22:32:53 2026
$end
$version
	Icarus Verilog
$end
$timescale
	1ps
$end
$scope module tb_full_adder $end
$var wire 1 ! s $end
$var wire 1 " cout $end
$var reg 1 # a $end
$var reg 1 $ b $end
$var reg 1 % cin $end
$var reg 2 & expected [1:0] $end
$var integer 32 ' checked [31:0] $end
$var integer 32 ( n [31:0] $end
$scope module dut $end
$var wire 1 # a $end
$var wire 1 $ b $end
$var wire 1 % cin $end
$var wire 1 " cout $end
$var wire 1 ) sum1 $end
$var wire 1 ! s $end
$var wire 1 * carry2 $end
$var wire 1 + carry1 $end
$scope module HA1 $end
$var wire 1 # a $end
$var wire 1 $ b $end
$var wire 1 + c $end
$var wire 1 ) s $end
$upscope $end
$scope module HA2 $end
$var wire 1 ) a $end
$var wire 1 % b $end
$var wire 1 * c $end
$var wire 1 ! s $end
$upscope $end
$upscope $end
$upscope $end
$enddefinitions $end
$comment Show the parameter values. $end
$dumpall
$end
#0
$dumpvars
0+
0*
0)
b0 (
b0 '
b0 &
0%
0$
0#
0"
0!
$end
#10000
1!
b1 &
1%
b1 (
b1 '
#20000
1)
1!
1$
0%
b10 (
b10 '
#30000
1"
0!
1*
b10 &
1%
b11 (
b11 '
#40000
0"
1!
0*
b1 &
1#
0$
0%
b100 (
b100 '
#50000
1"
0!
1*
b10 &
1%
b101 (
b101 '
#60000
0)
1+
0!
0*
1$
0%
b110 (
b110 '
#70000
1!
b11 &
1%
b111 (
b111 '
#80000
b1000 (
b1000 '
