LAB2/lab2_05_piso/src/piso4.v
`timescale 1ns/1ps

module piso4(

    input wire clk, input wire rst, input wire load, input wire enable, input wire [3:0] data_in,
    output wire serial_out, output reg [3:0] value

);

    assign serial_out = value[3];

    always @(posedge clk) begin
        if (rst)
            value <= 4'd0;
        else if (load)
            value <= data_in;
        else if (enable)
            value <= {value[2:0], 1'b0};
    end

endmodule

LAB2/lab2_05_piso/sim/tb_piso4.sv
`timescale 1ns/1ps

module tb_piso4;

    reg clk=0, rst=1;
    integer checks=0;

    always #5 clk=~clk;

    task step;
    begin
        @(posedge clk);
        #1;
    end
    endtask

    task check(input condition, input [8*100-1:0] description);
    begin
        checks=checks+1;
        if (condition !== 1'b1) begin
            $display("LAB2_FAIL %0s time=%0t",description,$time);
            $fatal(1,"check failed");
        end
    end
    endtask

    task finish;
    begin
        $display("LAB2_PASS piso4 checks=%0d",checks);
        $finish;
    end
    endtask

    initial begin
        $dumpfile("wave.vcd");
        $dumpvars(0,tb_piso4);
    end

    initial begin
        #100000;
        $fatal(1,"watchdog timeout");
    end

    reg load=0, enable=0;
    reg [3:0] data_in=0;
    wire serial_out;
    wire [3:0] value;

    piso4 dut(
        clk,
        rst,
        load,
        enable,
        data_in,
        serial_out,
        value
    );

    integer word, bit_number;

    initial begin
        step;
        check(value===0,"reset");
        rst=0;

        for(word=0; word<16; word=word+1) begin
            data_in=word;
            load=1;
            enable=1;
            step;
            check(value===word,"load beats shift");

            load=0;
            enable=0;
            step;
            check(value===word,"hold");

            enable=1;

            for(bit_number=3; bit_number>=0; bit_number=bit_number-1) begin
                check(serial_out===((word>>bit_number)&1),
                      "MSB first before edge");
                step;
            end

            check(value===0,"four shifts zero fill");
        end

        rst=1;
        load=1;
        data_in=15;
        step;
        check(value===0,"reset beats load");

        finish;
    end

endmodule

LAB2/lab2_05_piso/build/sim/run-f0d00823b41e4182a560c25aad89de6a/wave.vcd
$date
	Mon Sep 21 12:37:42 2026
$end
$version
	Icarus Verilog
$end
$timescale
	1ps
$end
$scope module tb_piso4 $end
$var wire 4 ! value [3:0] $end
$var wire 1 " serial_out $end
$var reg 1 # clk $end
$var reg 4 $ data_in [3:0] $end
$var reg 1 % enable $end
$var reg 1 & load $end
$var reg 1 ' rst $end
$var integer 32 ( bit_number [31:0] $end
$var integer 32 ) checks [31:0] $end
$var integer 32 * word [31:0] $end
$scope module dut $end
$var wire 1 # clk $end
$var wire 4 + data_in [3:0] $end
$var wire 1 % enable $end
$var wire 1 & load $end
$var wire 1 ' rst $end
$var wire 1 " serial_out $end
$var reg 4 , value [3:0] $end
$upscope $end
$scope task check $end
$var reg 1 - condition $end
$var reg 800 . description [799:0] $end
$upscope $end
$scope task finish $end
$upscope $end
$scope task step $end
$upscope $end
$upscope $end
$enddefinitions $end
$comment Show the parameter values. $end
$dumpall
$end
#0
$dumpvars
bx .
x-
bx ,
b0 +
bx *
b0 )
bx (
1'
0&
0%
b0 $
0#
x"
bx !
$end
#5000
0"
b0 !
b0 ,
1#
#6000
1%
1&
b0 *
0'
b1 )
b111001001100101011100110110010101110100 .
1-
#10000
0#
#15000
1#
#16000
0%
0&
b10 )
b1101100011011110110000101100100001000000110001001100101011000010111010001110011001000000111001101101000011010010110011001110100 .
#20000
0#
#25000
1#
#26000
b11 (
1%
b100 )
b10011010101001101000010001000000110011001101001011100100111001101110100001000000110001001100101011001100110111101110010011001010010000001100101011001000110011101100101 .
#30000
0#
#35000
1#
#36000
b101 )
b10 (
#40000
0#
#45000
1#
#46000
b110 )
b1 (
#50000
0#
#55000
1#
#56000
b111 )
b0 (
#60000
0#
#65000
1#
#66000
1&
b1 $
b1 +
b1 *
b1000 )
b11001100110111101110101011100100010000001110011011010000110100101100110011101000111001100100000011110100110010101110010011011110010000001100110011010010110110001101100 .
b11111111111111111111111111111111 (
#70000
0#
#75000
1"
b1 !
b1 ,
1#
#76000
0%
0&
b1001 )
b1101100011011110110000101100100001000000110001001100101011000010111010001110011001000000111001101101000011010010110011001110100 .
#80000
0#
#85000
1#
#86000
0-
b11 (
1%
b1011 )
b10011010101001101000010001000000110011001101001011100100111001101110100001000000110001001100101011001100110111101110010011001010010000001100101011001000110011101100101 .
