LAB3/lab3_19_led_pwm/src/pwm_channel.v
`timescale 1ns/1ps

module pwm_channel #(
    parameter integer PERIOD_CYCLES = 50_000,
    parameter integer LEVELS = 10
)(
    input  wire clk,
    input  wire rst_p,
    input  wire [3:0] level,
    output reg  pwm
);

    localparam integer COUNT_WIDTH =
        (PERIOD_CYCLES < 2) ? 1 : $clog2(PERIOD_CYCLES);

    reg [COUNT_WIDTH-1:0] count;
    integer threshold;

    always @* begin
        if (level >= LEVELS)
            threshold = PERIOD_CYCLES;
        else
            threshold = (PERIOD_CYCLES * level) / LEVELS;
    end

    always @(posedge clk or posedge rst_p) begin
        if (rst_p) begin
            count <= {COUNT_WIDTH{1'b0}};
            pwm <= 1'b0;
        end else begin
            pwm <= (count < threshold);
            if (count == PERIOD_CYCLES - 1)
                count <= {COUNT_WIDTH{1'b0}};
            else
                count <= count + 1'b1;
        end
    end
endmodule

LAB3/lab3_19_led_pwm/src/button_onepulse.v
`timescale 1ns/1ps

module button_onepulse #(
    parameter integer STABLE_CYCLES = 1_000_000
)(
    input wire clk,
    input wire rst_p,
    input wire button,
    output reg pulse
);

    (* ASYNC_REG = "TRUE" *) reg button_meta;
    (* ASYNC_REG = "TRUE" *) reg button_sync;

    localparam integer COUNT_WIDTH =
        (STABLE_CYCLES < 2) ? 1 : $clog2(STABLE_CYCLES);

    reg [COUNT_WIDTH-1:0] stable_count;
    reg accepted;

    always @(posedge clk or posedge rst_p) begin
        if (rst_p) begin
            button_meta <= 1'b0;
            button_sync <= 1'b0;
        end else begin
            button_meta <= button;
            button_sync <= button_meta;
        end
    end

    always @(posedge clk or posedge rst_p) begin
        if (rst_p) begin
            stable_count <= {COUNT_WIDTH{1'b0}};
            accepted <= 1'b0;
            pulse <= 1'b0;
        end else begin
            pulse <= 1'b0;

            if (button_sync == accepted) begin
                stable_count <= {COUNT_WIDTH{1'b0}};
            end else if (stable_count == STABLE_CYCLES - 1) begin
                stable_count <= {COUNT_WIDTH{1'b0}};
                accepted <= button_sync;
                pulse <= button_sync;
            end else begin
                stable_count <= stable_count + 1'b1;
            end
        end
    end

endmodule

LAB3/lab3_19_led_pwm/src/lab3_led_pwm.v
`timescale 1ns/1ps

module lab3_led_pwm #(
    parameter integer CLK_HZ = 50_000_000,
    parameter integer PWM_HZ = 1_000,
    parameter integer LEVELS = 10,
    parameter integer DEBOUNCE_CYCLES = 1_000_000
)(
    input wire clk_50mhz,
    input wire rst_p,
    input wire button,
    output wire [7:0] led
);

    wire press;
    wire pwm;
    reg [3:0] level;

    button_onepulse #(
        .STABLE_CYCLES(DEBOUNCE_CYCLES)
    ) u_button (
        .clk(clk_50mhz),
        .rst_p(rst_p),
        .button(button),
        .pulse(press)
    );

    always @(posedge clk_50mhz or posedge rst_p) begin
        
        if (rst_p)
            level <= 4'd0;
        else if (press)
            level <= (level == LEVELS) ? 4'd0 : level + 1'b1;
    end

    pwm_channel #(
        .PERIOD_CYCLES(CLK_HZ / PWM_HZ),
        .LEVELS(LEVELS)
    ) u_pwm (
        .clk(clk_50mhz),
        .rst_p(rst_p),
        .level(level),
        .pwm(pwm)
    );

    assign led = {8{pwm}};

endmodule

LAB3/lab3_19_led_pwm/sim/tb_led_pwm.sv
`timescale 1ns/1ps

module tb_led_pwm;

    reg clk_50mhz=0, rst_p=1, button=0;
    wire [7:0] led;
    integer checks=0, high_count, i;

    always #10 clk_50mhz=~clk_50mhz;

    lab3_led_pwm #(
        .CLK_HZ(1000),
        .PWM_HZ(100),
        .LEVELS(10),
        .DEBOUNCE_CYCLES(2)
    ) dut (
        .clk_50mhz(clk_50mhz),
        .rst_p(rst_p),
        .button(button),
        .led(led)
    );

    task press_button;
    begin
        button=1;
        repeat(6) @(posedge clk_50mhz);
        button=0;
        repeat(6) @(posedge clk_50mhz);
    end
    endtask

    task expect_level(input integer expected);
    begin
        wait(dut.u_pwm.count==0);
        high_count=0;

        for(i=0;i<10;i=i+1) begin
            @(posedge clk_50mhz);
            #1;
            if(led[0])
                high_count=high_count+1;
        end

        if(high_count!==expected)
            $fatal(1,"level=%0d high=%0d",expected,high_count);

        checks=checks+1;
    end
    endtask

    initial begin
        $dumpfile("wave.vcd");
        $dumpvars(0,tb_led_pwm);

        repeat(3) @(posedge clk_50mhz);
        rst_p=0;

        expect_level(0);

        repeat(3)
            press_button();
        expect_level(3);


        repeat(7)
            press_button();

        expect_level(10);

        press_button();
        expect_level(0);

        $display("LAB3_LED_PWM_PASS checks=%0d",checks);
        $finish;
    end

    initial begin
        #20000;
        $fatal(1,"timeout");
    end

endmodule

LAB3/lab3_19_led_pwm/build/sim/run-52efbf2e500947b48fff016c71c7fb26/wave.vcd
$date
	Mon Sep 28 02:35:37 2026
$end
$version
	Icarus Verilog
$end
$timescale
	1ps
$end
$scope module tb_led_pwm $end
$var wire 8 ! led [7:0] $end
$var reg 1 " button $end
$var reg 1 # clk_50mhz $end
$var reg 1 $ rst_p $end
$var integer 32 % checks [31:0] $end
$var integer 32 & high_count [31:0] $end
$var integer 32 ' i [31:0] $end
$scope module dut $end
$var wire 1 " button $end
$var wire 1 # clk_50mhz $end
$var wire 1 $ rst_p $end
$var wire 1 ( pwm $end
$var wire 1 ) press $end
$var wire 8 * led [7:0] $end
$var parameter 32 + CLK_HZ $end
$var parameter 32 , DEBOUNCE_CYCLES $end
$var parameter 32 - LEVELS $end
$var parameter 32 . PWM_HZ $end
$var reg 4 / level [3:0] $end
$scope module u_button $end
$var wire 1 " button $end
$var wire 1 # clk $end
$var wire 1 $ rst_p $end
$var parameter 32 0 COUNT_WIDTH $end
$var parameter 32 1 STABLE_CYCLES $end
$var reg 1 2 accepted $end
$var reg 1 3 button_meta $end
$var reg 1 4 button_sync $end
$var reg 1 ) pulse $end
$var reg 1 5 stable_count $end
$upscope $end
$scope module u_pwm $end
$var wire 1 # clk $end
$var wire 4 6 level [3:0] $end
$var wire 1 $ rst_p $end
$var parameter 32 7 COUNT_WIDTH $end
$var parameter 32 8 LEVELS $end
$var parameter 32 9 PERIOD_CYCLES $end
$var reg 4 : count [3:0] $end
$var reg 1 ( pwm $end
$var integer 32 ; threshold [31:0] $end
$upscope $end
$upscope $end
$scope task expect_level $end
$var integer 32 < expected [31:0] $end
$upscope $end
$scope task press_button $end
$upscope $end
$upscope $end
$enddefinitions $end
$comment Show the parameter values. $end
$dumpall
b1010 9
b1010 8
b100 7
b10 1
b1 0
b1100100 .
b1010 -
b10 ,
b1111101000 +
$end
#0
$dumpvars
bx <
bx ;
bx :
bx 6
x5
x4
x3
x2
bx /
bx *
x)
x(
bx '
bx &
b0 %
1$
0#
0"
bx !
$end
#10000
b0 ;
04
03
0)
02
05
b0 !
b0 *
0(
b0 :
b0 /
b0 6
1#
#20000
0#
#30000
1#
#40000
0#
#50000
b1 :
b0 '
b0 &
b0 <
0$
1#
#60000
0#
#70000
b10 :
1#
#71000
b1 '
#80000
0#
#90000
b11 :
1#
#91000
b10 '
#100000
0#
#110000
b100 :
1#
#111000
b11 '
#120000
0#
#130000
b101 :
1#
#131000
b100 '
#140000
0#
#150000
b110 :
1#
#151000
b101 '
#160000
0#
#170000
b111 :
1#
#171000
b110 '
#180000
0#
#190000
b1000 :
1#
#191000
b111 '
#200000
0#
#210000
b1001 :
1#
#211000
b1000 '
#220000
0#
#230000
b0 :
1#
#231000
b1001 '
#240000
0#
#250000
b1 :
1#
#251000
1"
b1 %
b1010 '
#260000
0#
#270000
b10 :
13
1#
#280000
0#
#290000
14
b11 :
1#
#300000
0#
#310000
b100 :
15
1#
#320000
0#
#330000
1)
12
05
b101 :
1#
#340000
0#
#350000
b1 ;
b1 /
b1 6
b110 :
0)
1#
#360000
0#
#370000
03
b111 :
0"
1#
#380000
0#
#390000
b1000 :
04
1#
#400000
0#
#410000
15
b1001 :
1#
#420000
0#
#430000
b0 :
02
05
1#
#440000
0#
#450000
b1 :
b11111111 !
b11111111 *
1(
1#
#460000
0#
#470000
b10 :
b0 !
b0 *
0(
1#
#480000
0#
#490000
b11 :
b11 <
1#
#500000
0#
#510000
b100 :
1#
#520000
0#
#530000
b101 :
1#
#540000
0#
#550000
b110 :
1#
#560000
0#
#570000
b111 :
1#
#580000
0#
#590000
b1000 :
1#
#600000
0#
#610000
b1001 :
1#
#620000
0#
#630000
b0 '
b0 :
1#
#640000
0#
#650000
b1 :
b11111111 !
b11111111 *
1(
1#
#651000
b1 '
b1 &
#660000
0#
#670000
b10 :
b0 !
b0 *
0(
1#
#671000
b10 '
#680000
0#
#690000
b11 :
1#
#691000
b11 '
#700000
0#
#710000
b100 :
1#
#711000
b100 '
#720000
0#
#730000
b101 :
1#
#731000
b101 '
#740000
0#
#750000
b110 :
1#
#751000
b110 '
#760000
0#
#770000
b111 :
1#
#771000
b111 '
#780000
0#
#790000
b1000 :
1#
#791000
b1000 '
#800000
0#
#810000
b1001 :
1#
#811000
b1001 '
#820000
0#
#830000
b0 :
1#
#831000
b1010 '
