LAB2/lab2_05_piso/src/piso4.v
`timescale 1ns/1ps

module piso4(

    input wire clk, input wire rst, input wire load, input wire enable, input wire [3:0] data_in,
    output wire serial_out, output reg [3:0] value

);

    assign serial_out = value[3];

    always @(posedge clk) begin
        if (rst)
            value <= 4'd0;
        else if (load)
            value <= data_in;
        else if (enable)
            value <= {value[2:0], 1'b0};
    end

endmodule

LAB2/lab2_05_piso/sim/tb_piso4.sv
`timescale 1ns/1ps

module tb_piso4;

    reg clk=0, rst=1;
    integer checks=0;

    always #5 clk=~clk;

    task step;
    begin
        @(posedge clk);
        #1;
    end
    endtask

    task check(input condition, input [8*100-1:0] description);
    begin
        checks=checks+1;
        if (condition !== 1'b1) begin
            $display("LAB2_FAIL %0s time=%0t",description,$time);
            $fatal(1,"check failed");
        end
    end
    endtask

    task finish;
    begin
        $display("LAB2_PASS piso4 checks=%0d",checks);
        $finish;
    end
    endtask

    initial begin
        $dumpfile("wave.vcd");
        $dumpvars(0,tb_piso4);
    end

    initial begin
        #100000;
        $fatal(1,"watchdog timeout");
    end

    reg load=0, enable=0;
    reg [3:0] data_in=0;
    wire serial_out;
    wire [3:0] value;

    piso4 dut(
        clk,
        rst,
        load,
        enable,
        data_in,
        serial_out,
        value
    );

    integer word, bit_number;

    initial begin
        step;
        check(value===0,"reset");
        rst=0;

        for(word=0; word<16; word=word+1) begin
            data_in=word;
            load=1;
            enable=1;
            step;
            check(value===word,"load beats shift");

            load=0;
            enable=0;
            step;
            check(value===word,"hold");

            enable=1;

            for(bit_number=3; bit_number>=0; bit_number=bit_number-1) begin
                check(serial_out===((word>>bit_number)&1),
                      "MSB first before edge");
                step;
            end

            check(value===0,"four shifts zero fill");
        end

        rst=1;
        load=1;
        data_in=15;
        step;
        check(value===0,"reset beats load");

        finish;
    end

endmodule

LAB2/lab2_05_piso/build/sim/run-89038a0249ef430fa58a186c7dc6287e/wave.vcd
$date
	Mon Sep 21 09:47:30 2026
$end
$version
	Icarus Verilog
$end
$timescale
	1ps
$end
$scope module tb_piso4 $end
$var wire 4 ! value [3:0] $end
$var wire 1 " serial_out $end
$var reg 1 # clk $end
$var reg 4 $ data_in [3:0] $end
$var reg 1 % enable $end
$var reg 1 & load $end
$var reg 1 ' rst $end
$var integer 32 ( bit_number [31:0] $end
$var integer 32 ) checks [31:0] $end
$var integer 32 * word [31:0] $end
$scope module dut $end
$var wire 1 # clk $end
$var wire 4 + data_in [3:0] $end
$var wire 1 % enable $end
$var wire 1 & load $end
$var wire 1 ' rst $end
$var wire 1 " serial_out $end
$var reg 4 , value [3:0] $end
$upscope $end
$scope task check $end
$var reg 1 - condition $end
$var reg 800 . description [799:0] $end
$upscope $end
$scope task finish $end
$upscope $end
$scope task step $end
$upscope $end
$upscope $end
$enddefinitions $end
$comment Show the parameter values. $end
$dumpall
$end
#0
$dumpvars
bx .
x-
bx ,
b0 +
bx *
b0 )
bx (
1'
0&
0%
b0 $
0#
x"
bx !
$end
#5000
0"
b0 !
b0 ,
1#
#6000
1%
1&
b0 *
0'
b1 )
b111001001100101011100110110010101110100 .
1-
#10000
0#
#15000
1#
#16000
0%
0&
b10 )
b1101100011011110110000101100100001000000110001001100101011000010111010001110011001000000111001101101000011010010110011001110100 .
#20000
0#
#25000
1#
#26000
b11 (
1%
b100 )
b10011010101001101000010001000000110011001101001011100100111001101110100001000000110001001100101011001100110111101110010011001010010000001100101011001000110011101100101 .
#30000
0#
#35000
1#
#36000
b101 )
b10 (
#40000
0#
#45000
1#
#46000
b110 )
b1 (
#50000
0#
#55000
1#
#56000
b111 )
b0 (
#60000
0#
#65000
1#
#66000
1&
b1 $
b1 +
b1 *
b1000 )
b11001100110111101110101011100100010000001110011011010000110100101100110011101000111001100100000011110100110010101110010011011110010000001100110011010010110110001101100 .
b11111111111111111111111111111111 (
#70000
0#
#75000
b1 !
b1 ,
1#
#76000
0%
0&
b1001 )
b1101100011011110110000101100100001000000110001001100101011000010111010001110011001000000111001101101000011010010110011001110100 .
#80000
0#
#85000
1#
#86000
b11 (
1%
b1011 )
b10011010101001101000010001000000110011001101001011100100111001101110100001000000110001001100101011001100110111101110010011001010010000001100101011001000110011101100101 .
#90000
0#
#95000
b10 !
b10 ,
1#
#96000
b1100 )
b10 (
#100000
0#
#105000
b100 !
b100 ,
1#
#106000
b1101 )
b1 (
#110000
0#
#115000
1"
b1000 !
b1000 ,
1#
#116000
b1110 )
b0 (
#120000
0#
#125000
0"
b0 !
b0 ,
1#
#126000
1&
b10 $
b10 +
b10 *
b1111 )
b11001100110111101110101011100100010000001110011011010000110100101100110011101000111001100100000011110100110010101110010011011110010000001100110011010010110110001101100 .
b11111111111111111111111111111111 (
#130000
0#
#135000
b10 !
b10 ,
1#
#136000
0%
0&
b10000 )
b1101100011011110110000101100100001000000110001001100101011000010111010001110011001000000111001101101000011010010110011001110100 .
#140000
0#
#145000
1#
#146000
b11 (
1%
b10010 )
b10011010101001101000010001000000110011001101001011100100111001101110100001000000110001001100101011001100110111101110010011001010010000001100101011001000110011101100101 .
#150000
0#
#155000
b100 !
b100 ,
1#
#156000
b10011 )
b10 (
#160000
0#
#165000
1"
b1000 !
b1000 ,
1#
#166000
b10100 )
b1 (
#170000
0#
#175000
0"
b0 !
b0 ,
1#
#176000
b10101 )
b0 (
#180000
0#
#185000
1#
#186000
1&
b11 $
b11 +
b11 *
b10110 )
b11001100110111101110101011100100010000001110011011010000110100101100110011101000111001100100000011110100110010101110010011011110010000001100110011010010110110001101100 .
b11111111111111111111111111111111 (
#190000
0#
#195000
b11 !
b11 ,
1#
#196000
0%
0&
b10111 )
b1101100011011110110000101100100001000000110001001100101011000010111010001110011001000000111001101101000011010010110011001110100 .
#200000
0#
#205000
1#
#206000
b11 (
1%
b11001 )
b10011010101001101000010001000000110011001101001011100100111001101110100001000000110001001100101011001100110111101110010011001010010000001100101011001000110011101100101 .
#210000
0#
#215000
b110 !
b110 ,
1#
#216000
b11010 )
b10 (
#220000
0#
#225000
1"
b1100 !
b1100 ,
1#
#226000
b11011 )
b1 (
#230000
0#
#235000
b1000 !
b1000 ,
1#
#236000
b11100 )
b0 (
#240000
0#
#245000
0"
b0 !
b0 ,
1#
#246000
1&
b100 $
b100 +
b100 *
b11101 )
b11001100110111101110101011100100010000001110011011010000110100101100110011101000111001100100000011110100110010101110010011011110010000001100110011010010110110001101100 .
b11111111111111111111111111111111 (
#250000
0#
#255000
b100 !
b100 ,
1#
#256000
0%
0&
b11110 )
b1101100011011110110000101100100001000000110001001100101011000010111010001110011001000000111001101101000011010010110011001110100 .
#260000
0#
#265000
1#
#266000
b11 (
1%
b100000 )
b10011010101001101000010001000000110011001101001011100100111001101110100001000000110001001100101011001100110111101110010011001010010000001100101011001000110011101100101 .
#270000
0#
#275000
1"
b1000 !
b1000 ,
1#
#276000
b100001 )
b10 (
#280000
0#
#285000
0"
b0 !
b0 ,
1#
#286000
b100010 )
b1 (
#290000
0#
#295000
1#
#296000
b100011 )
b0 (
#300000
0#
#305000
1#
#306000
1&
b101 $
b101 +
b101 *
b100100 )
b11001100110111101110101011100100010000001110011011010000110100101100110011101000111001100100000011110100110010101110010011011110010000001100110011010010110110001101100 .
b11111111111111111111111111111111 (
#310000
0#
#315000
b101 !
b101 ,
1#
#316000
0%
0&
b100101 )
b1101100011011110110000101100100001000000110001001100101011000010111010001110011001000000111001101101000011010010110011001110100 .
#320000
0#
#325000
1#
#326000
b11 (
1%
b100111 )
b10011010101001101000010001000000110011001101001011100100111001101110100001000000110001001100101011001100110111101110010011001010010000001100101011001000110011101100101 .
#330000
0#
#335000
1"
b1010 !
b1010 ,
1#
#336000
b101000 )
b10 (
#340000
0#
#345000
0"
b100 !
b100 ,
1#
#346000
b101001 )
b1 (
#350000
0#
#355000
1"
b1000 !
b1000 ,
1#
#356000
b101010 )
b0 (
#360000
0#
#365000
0"
b0 !
b0 ,
1#
#366000
1&
b110 $
b110 +
b110 *
b101011 )
b11001100110111101110101011100100010000001110011011010000110100101100110011101000111001100100000011110100110010101110010011011110010000001100110011010010110110001101100 .
b11111111111111111111111111111111 (
#370000
0#
#375000
b110 !
b110 ,
1#
#376000
0%
0&
b101100 )
b1101100011011110110000101100100001000000110001001100101011000010111010001110011001000000111001101101000011010010110011001110100 .
#380000
0#
#385000
1#
#386000
b11 (
1%
b101110 )
b10011010101001101000010001000000110011001101001011100100111001101110100001000000110001001100101011001100110111101110010011001010010000001100101011001000110011101100101 .
#390000
0#
#395000
1"
b1100 !
b1100 ,
1#
#396000
b101111 )
b10 (
#400000
0#
#405000
b1000 !
b1000 ,
1#
#406000
b110000 )
b1 (
#410000
0#
#415000
0"
b0 !
b0 ,
1#
#416000
b110001 )
b0 (
#420000
0#
#425000
1#
#426000
1&
b111 $
b111 +
b111 *
b110010 )
b11001100110111101110101011100100010000001110011011010000110100101100110011101000111001100100000011110100110010101110010011011110010000001100110011010010110110001101100 .
b11111111111111111111111111111111 (
#430000
0#
#435000
b111 !
b111 ,
1#
#436000
0%
0&
b110011 )
b1101100011011110110000101100100001000000110001001100101011000010111010001110011001000000111001101101000011010010110011001110100 .
#440000
0#
#445000
1#
#446000
b11 (
1%
b110101 )
b10011010101001101000010001000000110011001101001011100100111001101110100001000000110001001100101011001100110111101110010011001010010000001100101011001000110011101100101 .
#450000
0#
#455000
1"
b1110 !
b1110 ,
1#
#456000
b110110 )
b10 (
#460000
0#
#465000
b1100 !
b1100 ,
1#
#466000
b110111 )
b1 (
#470000
0#
#475000
b1000 !
b1000 ,
1#
#476000
b111000 )
b0 (
#480000
0#
#485000
0"
b0 !
b0 ,
1#
#486000
1&
b1000 $
b1000 +
b1000 *
b111001 )
b11001100110111101110101011100100010000001110011011010000110100101100110011101000111001100100000011110100110010101110010011011110010000001100110011010010110110001101100 .
b11111111111111111111111111111111 (
#490000
0#
#495000
1"
b1000 !
b1000 ,
1#
#496000
0%
0&
b111010 )
b1101100011011110110000101100100001000000110001001100101011000010111010001110011001000000111001101101000011010010110011001110100 .
#500000
0#
#505000
1#
#506000
b11 (
1%
b111100 )
b10011010101001101000010001000000110011001101001011100100111001101110100001000000110001001100101011001100110111101110010011001010010000001100101011001000110011101100101 .
#510000
0#
#515000
0"
b0 !
b0 ,
1#
#516000
b111101 )
b10 (
#520000
0#
#525000
1#
#526000
b111110 )
b1 (
#530000
0#
#535000
1#
#536000
b111111 )
b0 (
#540000
0#
#545000
1#
#546000
1&
b1001 $
b1001 +
b1001 *
b1000000 )
b11001100110111101110101011100100010000001110011011010000110100101100110011101000111001100100000011110100110010101110010011011110010000001100110011010010110110001101100 .
b11111111111111111111111111111111 (
#550000
0#
#555000
1"
b1001 !
b1001 ,
1#
#556000
0%
0&
b1000001 )
b1101100011011110110000101100100001000000110001001100101011000010111010001110011001000000111001101101000011010010110011001110100 .
#560000
0#
#565000
1#
#566000
b11 (
1%
b1000011 )
b10011010101001101000010001000000110011001101001011100100111001101110100001000000110001001100101011001100110111101110010011001010010000001100101011001000110011101100101 .
#570000
0#
#575000
0"
b10 !
b10 ,
1#
#576000
b1000100 )
b10 (
#580000
0#
#585000
b100 !
b100 ,
1#
#586000
b1000101 )
b1 (
#590000
0#
#595000
1"
b1000 !
b1000 ,
1#
#596000
b1000110 )
b0 (
#600000
0#
#605000
0"
b0 !
b0 ,
1#
#606000
1&
b1010 $
b1010 +
b1010 *
b1000111 )
b11001100110111101110101011100100010000001110011011010000110100101100110011101000111001100100000011110100110010101110010011011110010000001100110011010010110110001101100 .
b11111111111111111111111111111111 (
#610000
0#
#615000
1"
b1010 !
b1010 ,
1#
#616000
0%
0&
b1001000 )
b1101100011011110110000101100100001000000110001001100101011000010111010001110011001000000111001101101000011010010110011001110100 .
#620000
0#
#625000
1#
#626000
b11 (
1%
b1001010 )
b10011010101001101000010001000000110011001101001011100100111001101110100001000000110001001100101011001100110111101110010011001010010000001100101011001000110011101100101 .
#630000
0#
#635000
0"
b100 !
b100 ,
1#
#636000
b1001011 )
b10 (
#640000
0#
#645000
1"
b1000 !
b1000 ,
1#
#646000
b1001100 )
b1 (
#650000
0#
#655000
0"
b0 !
b0 ,
1#
#656000
b1001101 )
b0 (
#660000
0#
#665000
1#
#666000
1&
b1011 $
b1011 +
b1011 *
b1001110 )
b11001100110111101110101011100100010000001110011011010000110100101100110011101000111001100100000011110100110010101110010011011110010000001100110011010010110110001101100 .
b11111111111111111111111111111111 (
#670000
0#
#675000
1"
b1011 !
b1011 ,
1#
#676000
0%
0&
b1001111 )
b1101100011011110110000101100100001000000110001001100101011000010111010001110011001000000111001101101000011010010110011001110100 .
#680000
0#
#685000
1#
#686000
b11 (
1%
b1010001 )
b10011010101001101000010001000000110011001101001011100100111001101110100001000000110001001100101011001100110111101110010011001010010000001100101011001000110011101100101 .
#690000
0#
#695000
0"
b110 !
b110 ,
1#
#696000
b1010010 )
b10 (
#700000
0#
#705000
1"
b1100 !
b1100 ,
1#
#706000
b1010011 )
b1 (
#710000
0#
#715000
b1000 !
b1000 ,
1#
#716000
b1010100 )
b0 (
#720000
0#
#725000
0"
b0 !
b0 ,
1#
#726000
1&
b1100 $
b1100 +
b1100 *
b1010101 )
b11001100110111101110101011100100010000001110011011010000110100101100110011101000111001100100000011110100110010101110010011011110010000001100110011010010110110001101100 .
b11111111111111111111111111111111 (
#730000
0#
#735000
1"
b1100 !
b1100 ,
1#
#736000
0%
0&
b1010110 )
b1101100011011110110000101100100001000000110001001100101011000010111010001110011001000000111001101101000011010010110011001110100 .
#740000
0#
#745000
1#
#746000
b11 (
1%
b1011000 )
b10011010101001101000010001000000110011001101001011100100111001101110100001000000110001001100101011001100110111101110010011001010010000001100101011001000110011101100101 .
#750000
0#
#755000
b1000 !
b1000 ,
1#
#756000
b1011001 )
b10 (
#760000
0#
#765000
0"
b0 !
b0 ,
1#
#766000
b1011010 )
b1 (
#770000
0#
#775000
1#
#776000
b1011011 )
b0 (
#780000
0#
#785000
1#
#786000
1&
b1101 $
b1101 +
b1101 *
b1011100 )
b11001100110111101110101011100100010000001110011011010000110100101100110011101000111001100100000011110100110010101110010011011110010000001100110011010010110110001101100 .
b11111111111111111111111111111111 (
#790000
0#
#795000
1"
b1101 !
b1101 ,
1#
#796000
0%
0&
b1011101 )
b1101100011011110110000101100100001000000110001001100101011000010111010001110011001000000111001101101000011010010110011001110100 .
#800000
0#
#805000
1#
#806000
b11 (
1%
b1011111 )
b10011010101001101000010001000000110011001101001011100100111001101110100001000000110001001100101011001100110111101110010011001010010000001100101011001000110011101100101 .
#810000
0#
#815000
b1010 !
b1010 ,
1#
#816000
b1100000 )
b10 (
#820000
0#
#825000
0"
b100 !
b100 ,
1#
#826000
b1100001 )
b1 (
#830000
0#
#835000
1"
b1000 !
b1000 ,
1#
#836000
b1100010 )
b0 (
#840000
0#
#845000
0"
b0 !
b0 ,
1#
#846000
1&
b1110 $
b1110 +
b1110 *
b1100011 )
b11001100110111101110101011100100010000001110011011010000110100101100110011101000111001100100000011110100110010101110010011011110010000001100110011010010110110001101100 .
b11111111111111111111111111111111 (
#850000
0#
#855000
1"
b1110 !
b1110 ,
1#
#856000
0%
0&
b1100100 )
b1101100011011110110000101100100001000000110001001100101011000010111010001110011001000000111001101101000011010010110011001110100 .
#860000
0#
#865000
1#
#866000
b11 (
1%
b1100110 )
b10011010101001101000010001000000110011001101001011100100111001101110100001000000110001001100101011001100110111101110010011001010010000001100101011001000110011101100101 .
#870000
0#
#875000
b1100 !
b1100 ,
1#
#876000
b1100111 )
b10 (
#880000
0#
#885000
b1000 !
b1000 ,
1#
#886000
b1101000 )
b1 (
#890000
0#
#895000
0"
b0 !
b0 ,
1#
#896000
b1101001 )
b0 (
#900000
0#
#905000
1#
#906000
1&
b1111 $
b1111 +
b1111 *
b1101010 )
b11001100110111101110101011100100010000001110011011010000110100101100110011101000111001100100000011110100110010101110010011011110010000001100110011010010110110001101100 .
b11111111111111111111111111111111 (
#910000
0#
#915000
1"
b1111 !
b1111 ,
1#
#916000
0%
0&
b1101011 )
b1101100011011110110000101100100001000000110001001100101011000010111010001110011001000000111001101101000011010010110011001110100 .
#920000
0#
#925000
1#
#926000
b11 (
1%
b1101101 )
b10011010101001101000010001000000110011001101001011100100111001101110100001000000110001001100101011001100110111101110010011001010010000001100101011001000110011101100101 .
#930000
0#
#935000
b1110 !
b1110 ,
1#
#936000
b1101110 )
b10 (
#940000
0#
#945000
b1100 !
b1100 ,
1#
#946000
b1101111 )
b1 (
#950000
0#
#955000
b1000 !
b1000 ,
1#
#956000
b1110000 )
b0 (
#960000
0#
#965000
0"
b0 !
b0 ,
1#
#966000
1&
1'
b10000 *
b1110001 )
b11001100110111101110101011100100010000001110011011010000110100101100110011101000111001100100000011110100110010101110010011011110010000001100110011010010110110001101100 .
b11111111111111111111111111111111 (
#970000
0#
#975000
1#
#976000
b1110010 )
b1110010011001010111001101100101011101000010000001100010011001010110000101110100011100110010000001101100011011110110000101100100 .
